flake8_sql/__init__.py
flake8_sql/keywords.py
flake8_sql/linter.py
flake8_sql/parser.py
flake8_SQL-0.4.1.dist-info/LICENSE
flake8_SQL-0.4.1.dist-info/METADATA
flake8_SQL-0.4.1.dist-info/WHEEL
flake8_SQL-0.4.1.dist-info/entry_points.txt
flake8_SQL-0.4.1.dist-info/top_level.txt
flake8_SQL-0.4.1.dist-info/RECORD
