Metadata-Version: 2.1
Name: flake8-SQL
Version: 0.4.1
Summary: Flake8 plugin that checks SQL code against opinionated style rules
Home-page: https://github.com/pgjones/flake8-sql
Author: P G Jones
Author-email: philip.graham.jones@googlemail.com
License: MIT
Keywords: flake8,plugin,sql
Platform: UNKNOWN
Classifier: Development Status :: 3 - Alpha
Classifier: Environment :: Console
Classifier: Framework :: Flake8
Classifier: Intended Audience :: Developers
Classifier: License :: OSI Approved :: MIT License
Classifier: Operating System :: OS Independent
Classifier: Programming Language :: Python :: 3
Classifier: Programming Language :: Python :: 3.5
Classifier: Programming Language :: Python :: 3.6
Classifier: Programming Language :: Python :: 3.7
Classifier: Programming Language :: Python :: 3.8
Classifier: Programming Language :: Python
Classifier: Topic :: Software Development :: Libraries :: Python Modules
Classifier: Topic :: Software Development :: Quality Assurance
Requires-Dist: flake8
Requires-Dist: setuptools
Requires-Dist: sqlparse
